docrobot/__init__.py
docrobot/form.py
docrobot/form.ui
docrobot/guimain.pyw
docrobot-1.1.11.dist-info/METADATA
docrobot-1.1.11.dist-info/WHEEL
docrobot-1.1.11.dist-info/entry_points.txt
docrobot-1.1.11.dist-info/licenses/LICENSE
docrobot-1.1.11.dist-info/RECORD
