Metadata-Version: 2.4
Name: docrobot
Version: 1.1.11
Summary: 一个文档自动化处理工具
Project-URL: Homepage, https://github.com/icehong/docrobot
Project-URL: Bug Tracker, https://github.com/icehong/docrobot/issues
Author-email: Xu Hong <icehong@gmail.com>
License-File: LICENSE
Classifier: License :: OSI Approved :: MIT License
Classifier: Operating System :: Microsoft :: Windows
Classifier: Programming Language :: Python :: 3
Requires-Python: >=3.10
Requires-Dist: openpyxl
Requires-Dist: pyside6
Requires-Dist: python-docx
Requires-Dist: pywin32
